pips3/__init__.py
pips3/_version.py
pips3/base.py
pips3/cli.py
pips3/exceptions.py
pips3-0.4.2.dist-info/LICENSE
pips3-0.4.2.dist-info/METADATA
pips3-0.4.2.dist-info/WHEEL
pips3-0.4.2.dist-info/entry_points.txt
pips3-0.4.2.dist-info/top_level.txt
pips3-0.4.2.dist-info/RECORD
